vtrtool/__init__.py
vtrtool/aux_funcs.py
vtrtool/ttr.py
vtrtool/vtrmodel.py
vtrtool/vtrtool_script.py
vtrtool/scripts/__init__.py
vtrtool/scripts/vtrconvert.py
vtrtool/scripts/vtrshow.py
vtrtool/scripts/vtrtool.py
vtrtool-0.8.8.dist-info/LICENSE
vtrtool-0.8.8.dist-info/METADATA
vtrtool-0.8.8.dist-info/WHEEL
vtrtool-0.8.8.dist-info/entry_points.txt
vtrtool-0.8.8.dist-info/top_level.txt
vtrtool-0.8.8.dist-info/RECORD
