Metadata-Version: 2.1
Name: vtrtool
Version: 0.8.8
Summary: Python utilities for Fullwave3D VTR model files
Home-page: http://not-yet
Author: Tim Lin (S-Cube)
Author-email: tlin@s-cube.com
License: 3-clause BSD
Keywords: fullwave3d vtr
Platform: UNKNOWN
Classifier: Development Status :: 3 - Alpha
Classifier: Topic :: Utilities
Classifier: Programming Language :: Python :: 2.7
Classifier: Programming Language :: Python :: 3
Classifier: License :: OSI Approved :: BSD License
Requires-Dist: future
Requires-Dist: numpy
Requires-Dist: docopt
Requires-Dist: segyio (>=1.8)
